dou_verify/__init__.py
dou_verify-0.1.0.dist-info/WHEEL
dou_verify-0.1.0.dist-info/METADATA
dou_verify-0.1.0.dist-info/RECORD
