Metadata-Version: 2.1
Name: dou-verify
Version: 0.1.0
Summary: 
Author: satoru
Author-email: satorulogic@gmail.com
Requires-Python: >=3.10,<4.0
Classifier: Programming Language :: Python :: 3
Classifier: Programming Language :: Python :: 3.10
Requires-Dist: pyquery (>=1.4.3,<2.0.0)
Requires-Dist: requests (>=2.27.1,<3.0.0)
